{
  "black": "/Users/vid/.codex/generated_images/019f3251-7389-7470-a8eb-e2c8acbbf565/ig_02317fd2a3acfe8f016a4ce47978d081919dcecace444b445a.png",
  "candidates": [
    {
      "name": "black-white",
      "negative_diff_ratio": 0.07213147481282552,
      "out": "/tmp/alphakit-add-demo-photorealistic-product-cutouts/photorealistic-product-cutouts-black-white.png",
      "profile_pass": false,
      "report": {
        "alpha_channel_count": 3,
        "alpha_max": 1.0,
        "alpha_min": 0.0,
        "candidate_name": "black-white",
        "channel_spread_max": 0.18251100182533264,
        "channel_spread_mean": 0.0020984571892768145,
        "channel_spread_p95": 0.006665384396910667,
        "channel_spread_p99": 0.024032410234212875,
        "first": "/Users/vid/.codex/generated_images/019f3251-7389-7470-a8eb-e2c8acbbf565/ig_02317fd2a3acfe8f016a4ce47978d081919dcecace444b445a.png",
        "first_bg": [
          0.0,
          0.0,
          0.0
        ],
        "height": 1024,
        "max_negative_ratio": 0.03,
        "max_spread_max": 0.12,
        "max_spread_p95": 0.12,
        "max_spread_p99": 0.015,
        "max_too_high_ratio": 0.0,
        "negative_diff_ratio": 0.07213147481282552,
        "opaque_pixels": 136248,
        "out": "/tmp/alphakit-add-demo-photorealistic-product-cutouts/photorealistic-product-cutouts-black-white.png",
        "profile_pass": false,
        "quality_profile": "strict",
        "quality_profile_report": {
          "description": "Default extraction gate for committed demo assets.",
          "max_negative_ratio": 0.03,
          "max_spread_max": 0.12,
          "max_spread_p95": 0.12,
          "max_spread_p99": 0.015,
          "max_too_high_ratio": 0.0,
          "name": "strict",
          "requires_visual_qa": false,
          "snap_alpha_below": 20,
          "thresholds": {
            "max_negative_ratio": 0.03,
            "max_spread_max": 0.12,
            "max_spread_p95": 0.12,
            "max_spread_p99": 0.015,
            "max_too_high_ratio": 0.0
          }
        },
        "second": "/Users/vid/.codex/generated_images/019f3251-7389-7470-a8eb-e2c8acbbf565/ig_0d1459d1e601af22016a4ce4cb33dc81939dd08322317aefe8.png",
        "second_bg": [
          1.0,
          1.0,
          1.0
        ],
        "semi_transparent_pixels": 625000,
        "snap_alpha_below": 20,
        "strict_pass": false,
        "too_high_diff_ratio": 0.0,
        "transparent_pixels": 811616,
        "width": 1536
      },
      "returncode": 1,
      "stderr": "Background pair appears inconsistent or misaligned (candidate=black-white, profile=strict, p99=0.0240, max=0.1825, negative_diff_ratio=0.0721). Use --no-strict only if you accept artifacts.\n",
      "strict_pass": false
    },
    {
      "name": "black-green",
      "negative_diff_ratio": 0.029623667399088543,
      "out": "/tmp/alphakit-add-demo-photorealistic-product-cutouts/photorealistic-product-cutouts-black-green.png",
      "profile_pass": true,
      "report": {
        "alpha_channel_count": 1,
        "alpha_max": 1.0,
        "alpha_min": 0.00784313678741455,
        "candidate_name": "black-green",
        "channel_spread_max": 0.0,
        "channel_spread_mean": 0.0,
        "channel_spread_p95": 0.0,
        "channel_spread_p99": 0.0,
        "first": "/Users/vid/.codex/generated_images/019f3251-7389-7470-a8eb-e2c8acbbf565/ig_02317fd2a3acfe8f016a4ce47978d081919dcecace444b445a.png",
        "first_bg": [
          0.0,
          0.0,
          0.0
        ],
        "height": 1024,
        "max_negative_ratio": 0.03,
        "max_spread_max": 0.12,
        "max_spread_p95": 0.12,
        "max_spread_p99": 0.015,
        "max_too_high_ratio": 0.0,
        "negative_diff_ratio": 0.029623667399088543,
        "opaque_pixels": 99865,
        "out": "/tmp/alphakit-add-demo-photorealistic-product-cutouts/photorealistic-product-cutouts-black-green.png",
        "profile_pass": true,
        "quality_profile": "strict",
        "quality_profile_report": {
          "description": "Default extraction gate for committed demo assets.",
          "max_negative_ratio": 0.03,
          "max_spread_max": 0.12,
          "max_spread_p95": 0.12,
          "max_spread_p99": 0.015,
          "max_too_high_ratio": 0.0,
          "name": "strict",
          "requires_visual_qa": false,
          "snap_alpha_below": 20,
          "thresholds": {
            "max_negative_ratio": 0.03,
            "max_spread_max": 0.12,
            "max_spread_p95": 0.12,
            "max_spread_p99": 0.015,
            "max_too_high_ratio": 0.0
          }
        },
        "second": "/Users/vid/.codex/generated_images/019f3251-7389-7470-a8eb-e2c8acbbf565/ig_0df6ed071c7e267f016a4ce9db307c8191a465c3b93927a6f9.png",
        "second_bg": [
          0.0,
          1.0,
          0.0
        ],
        "semi_transparent_pixels": 1472999,
        "snap_alpha_below": 20,
        "strict_pass": true,
        "too_high_diff_ratio": 0.0,
        "transparent_pixels": 0,
        "width": 1536
      },
      "returncode": 0,
      "stderr": "",
      "strict_pass": true
    },
    {
      "name": "green-white",
      "negative_diff_ratio": 0.11950492858886719,
      "out": "/tmp/alphakit-add-demo-photorealistic-product-cutouts/photorealistic-product-cutouts-green-white.png",
      "profile_pass": false,
      "report": {
        "alpha_channel_count": 2,
        "alpha_max": 1.0,
        "alpha_min": 0.0,
        "candidate_name": "green-white",
        "channel_spread_max": 0.24313727021217346,
        "channel_spread_mean": 0.007255915552377701,
        "channel_spread_p95": 0.013725489377975464,
        "channel_spread_p99": 0.03333333134651184,
        "first": "/Users/vid/.codex/generated_images/019f3251-7389-7470-a8eb-e2c8acbbf565/ig_0df6ed071c7e267f016a4ce9db307c8191a465c3b93927a6f9.png",
        "first_bg": [
          0.0,
          1.0,
          0.0
        ],
        "height": 1024,
        "max_negative_ratio": 0.03,
        "max_spread_max": 0.12,
        "max_spread_p95": 0.12,
        "max_spread_p99": 0.015,
        "max_too_high_ratio": 0.0,
        "negative_diff_ratio": 0.11950492858886719,
        "opaque_pixels": 237979,
        "out": "/tmp/alphakit-add-demo-photorealistic-product-cutouts/photorealistic-product-cutouts-green-white.png",
        "profile_pass": false,
        "quality_profile": "strict",
        "quality_profile_report": {
          "description": "Default extraction gate for committed demo assets.",
          "max_negative_ratio": 0.03,
          "max_spread_max": 0.12,
          "max_spread_p95": 0.12,
          "max_spread_p99": 0.015,
          "max_too_high_ratio": 0.0,
          "name": "strict",
          "requires_visual_qa": false,
          "snap_alpha_below": 20,
          "thresholds": {
            "max_negative_ratio": 0.03,
            "max_spread_max": 0.12,
            "max_spread_p95": 0.12,
            "max_spread_p99": 0.015,
            "max_too_high_ratio": 0.0
          }
        },
        "second": "/Users/vid/.codex/generated_images/019f3251-7389-7470-a8eb-e2c8acbbf565/ig_0d1459d1e601af22016a4ce4cb33dc81939dd08322317aefe8.png",
        "second_bg": [
          1.0,
          1.0,
          1.0
        ],
        "semi_transparent_pixels": 1334845,
        "snap_alpha_below": 20,
        "strict_pass": false,
        "too_high_diff_ratio": 0.0,
        "transparent_pixels": 40,
        "width": 1536
      },
      "returncode": 1,
      "stderr": "Background pair appears inconsistent or misaligned (candidate=green-white, profile=strict, p99=0.0333, max=0.2431, negative_diff_ratio=0.1195). Use --no-strict only if you accept artifacts.\n",
      "strict_pass": false
    }
  ],
  "commands": {
    "black_green": [
      "/Users/vid/.cache/codex-runtimes/codex-primary-runtime/dependencies/python/bin/python3",
      "/Users/vid/generate-transparent-image-skill/scripts/alpha_from_background_pair.py",
      "--candidate-name",
      "black-green",
      "--first",
      "/Users/vid/.codex/generated_images/019f3251-7389-7470-a8eb-e2c8acbbf565/ig_02317fd2a3acfe8f016a4ce47978d081919dcecace444b445a.png",
      "--second",
      "/Users/vid/.codex/generated_images/019f3251-7389-7470-a8eb-e2c8acbbf565/ig_0df6ed071c7e267f016a4ce9db307c8191a465c3b93927a6f9.png",
      "--first-bg",
      "#000000",
      "--second-bg",
      "#00ff00",
      "--out",
      "/tmp/alphakit-add-demo-photorealistic-product-cutouts/photorealistic-product-cutouts-black-green.png",
      "--quality-profile",
      "strict",
      "--max-spread-p95",
      "0.12",
      "--max-spread-p99",
      "0.015",
      "--max-spread-max",
      "0.12",
      "--max-negative-ratio",
      "0.03",
      "--max-too-high-ratio",
      "0.0",
      "--json"
    ],
    "black_white": [
      "/Users/vid/.cache/codex-runtimes/codex-primary-runtime/dependencies/python/bin/python3",
      "/Users/vid/generate-transparent-image-skill/scripts/alpha_from_background_pair.py",
      "--candidate-name",
      "black-white",
      "--first",
      "/Users/vid/.codex/generated_images/019f3251-7389-7470-a8eb-e2c8acbbf565/ig_02317fd2a3acfe8f016a4ce47978d081919dcecace444b445a.png",
      "--second",
      "/Users/vid/.codex/generated_images/019f3251-7389-7470-a8eb-e2c8acbbf565/ig_0d1459d1e601af22016a4ce4cb33dc81939dd08322317aefe8.png",
      "--first-bg",
      "#000000",
      "--second-bg",
      "#ffffff",
      "--out",
      "/tmp/alphakit-add-demo-photorealistic-product-cutouts/photorealistic-product-cutouts-black-white.png",
      "--quality-profile",
      "strict",
      "--max-spread-p95",
      "0.12",
      "--max-spread-p99",
      "0.015",
      "--max-spread-max",
      "0.12",
      "--max-negative-ratio",
      "0.03",
      "--max-too-high-ratio",
      "0.0",
      "--json"
    ],
    "export_webp": [
      "/Users/vid/.cache/codex-runtimes/codex-primary-runtime/dependencies/python/bin/python3",
      "/Users/vid/generate-transparent-image-skill/scripts/export_image.py",
      "--input",
      "/tmp/alphakit-add-demo-photorealistic-product-cutouts/photorealistic-product-cutouts.png",
      "--format",
      "webp",
      "--out",
      "/tmp/alphakit-add-demo-photorealistic-product-cutouts/photorealistic-product-cutouts.webp",
      "--preserve-alpha",
      "--lossless",
      "--json"
    ],
    "green_white": [
      "/Users/vid/.cache/codex-runtimes/codex-primary-runtime/dependencies/python/bin/python3",
      "/Users/vid/generate-transparent-image-skill/scripts/alpha_from_background_pair.py",
      "--candidate-name",
      "green-white",
      "--first",
      "/Users/vid/.codex/generated_images/019f3251-7389-7470-a8eb-e2c8acbbf565/ig_0df6ed071c7e267f016a4ce9db307c8191a465c3b93927a6f9.png",
      "--second",
      "/Users/vid/.codex/generated_images/019f3251-7389-7470-a8eb-e2c8acbbf565/ig_0d1459d1e601af22016a4ce4cb33dc81939dd08322317aefe8.png",
      "--first-bg",
      "#00ff00",
      "--second-bg",
      "#ffffff",
      "--out",
      "/tmp/alphakit-add-demo-photorealistic-product-cutouts/photorealistic-product-cutouts-green-white.png",
      "--quality-profile",
      "strict",
      "--max-spread-p95",
      "0.12",
      "--max-spread-p99",
      "0.015",
      "--max-spread-max",
      "0.12",
      "--max-negative-ratio",
      "0.03",
      "--max-too-high-ratio",
      "0.0",
      "--json"
    ],
    "verify_png": [
      "/Users/vid/.cache/codex-runtimes/codex-primary-runtime/dependencies/python/bin/python3",
      "/Users/vid/generate-transparent-image-skill/scripts/verify_alpha.py",
      "/tmp/alphakit-add-demo-photorealistic-product-cutouts/photorealistic-product-cutouts.png",
      "--json"
    ],
    "verify_webp": [
      "/Users/vid/.cache/codex-runtimes/codex-primary-runtime/dependencies/python/bin/python3",
      "/Users/vid/generate-transparent-image-skill/scripts/verify_alpha.py",
      "/tmp/alphakit-add-demo-photorealistic-product-cutouts/photorealistic-product-cutouts.webp",
      "--json"
    ]
  },
  "demo_id": "photorealistic-product-cutouts",
  "export_webp": {
    "report": {
      "background": [
        255,
        255,
        255
      ],
      "flattened": false,
      "format": "webp",
      "input": "/tmp/alphakit-add-demo-photorealistic-product-cutouts/photorealistic-product-cutouts.png",
      "lossless": true,
      "out": "/tmp/alphakit-add-demo-photorealistic-product-cutouts/photorealistic-product-cutouts.webp",
      "preserve_alpha": true,
      "quality": 95,
      "source_has_alpha": true,
      "source_mode": "RGBA"
    },
    "returncode": 0,
    "stderr": ""
  },
  "final_paths": {
    "black": "/Users/vid/generate-transparent-image-skill/examples/pairs/photorealistic-product-cutouts-black.png",
    "green": "/Users/vid/generate-transparent-image-skill/examples/pairs/photorealistic-product-cutouts-green.png",
    "png": "/Users/vid/generate-transparent-image-skill/examples/transparent/photorealistic-product-cutouts.png",
    "report": "/Users/vid/generate-transparent-image-skill/examples/reports/photorealistic-product-cutouts.json",
    "webp": "/Users/vid/generate-transparent-image-skill/examples/transparent/photorealistic-product-cutouts.webp",
    "white": "/Users/vid/generate-transparent-image-skill/examples/pairs/photorealistic-product-cutouts-white.png"
  },
  "green": "/Users/vid/.codex/generated_images/019f3251-7389-7470-a8eb-e2c8acbbf565/ig_0df6ed071c7e267f016a4ce9db307c8191a465c3b93927a6f9.png",
  "height": 1024,
  "max_negative_ratio": 0.03,
  "quality_profile": "strict",
  "quality_profile_report": {
    "description": "Default extraction gate for committed demo assets.",
    "max_negative_ratio": 0.03,
    "max_spread_max": 0.12,
    "max_spread_p95": 0.12,
    "max_spread_p99": 0.015,
    "max_too_high_ratio": 0.0,
    "name": "strict",
    "requires_visual_qa": false,
    "snap_alpha_below": 20,
    "thresholds": {
      "max_negative_ratio": 0.03,
      "max_spread_max": 0.12,
      "max_spread_p95": 0.12,
      "max_spread_p99": 0.015,
      "max_too_high_ratio": 0.0
    }
  },
  "selected_candidate": "black-green",
  "selection_rule": "Selected the passing candidate with the lowest negative_diff_ratio.",
  "stage_png": "/tmp/alphakit-add-demo-photorealistic-product-cutouts/photorealistic-product-cutouts.png",
  "stage_webp": "/tmp/alphakit-add-demo-photorealistic-product-cutouts/photorealistic-product-cutouts.webp",
  "status": "passed",
  "verify_png": {
    "report": {
      "alpha_max": 255,
      "alpha_min": 0,
      "format": "PNG",
      "fully_opaque_pixels": 76312,
      "fully_transparent_pixels": 1005756,
      "has_alpha": true,
      "height": 1024,
      "mode": "RGBA",
      "path": "/tmp/alphakit-add-demo-photorealistic-product-cutouts/photorealistic-product-cutouts.png",
      "semi_transparent_pixels": 490796,
      "semi_transparent_ratio": 0.31203969319661456,
      "transparent_pixels": 1496552,
      "transparent_ratio": 0.9514821370442709,
      "width": 1536
    },
    "returncode": 0,
    "stderr": ""
  },
  "verify_webp": {
    "report": {
      "alpha_max": 255,
      "alpha_min": 0,
      "format": "WEBP",
      "fully_opaque_pixels": 76312,
      "fully_transparent_pixels": 1005756,
      "has_alpha": true,
      "height": 1024,
      "mode": "RGBA",
      "path": "/tmp/alphakit-add-demo-photorealistic-product-cutouts/photorealistic-product-cutouts.webp",
      "semi_transparent_pixels": 490796,
      "semi_transparent_ratio": 0.31203969319661456,
      "transparent_pixels": 1496552,
      "transparent_ratio": 0.9514821370442709,
      "width": 1536
    },
    "returncode": 0,
    "stderr": ""
  },
  "visual_qa_note": "",
  "visual_qa_passed": false,
  "visual_qa_required": false,
  "white": "/Users/vid/.codex/generated_images/019f3251-7389-7470-a8eb-e2c8acbbf565/ig_0d1459d1e601af22016a4ce4cb33dc81939dd08322317aefe8.png",
  "width": 1536
}
